__init__.py
xml_sanitizer.py
xml_sanitizer-0.1.1.dist-info/licenses/LICENSE
xml_sanitizer-0.1.1.dist-info/METADATA
xml_sanitizer-0.1.1.dist-info/WHEEL
xml_sanitizer-0.1.1.dist-info/top_level.txt
xml_sanitizer-0.1.1.dist-info/RECORD
