Metadata-Version: 2.4
Name: xml-sanitizer
Version: 0.1.1
Summary: Safely escape ampersands in XML without double-encoding
Author-email: Tanveer Mustafa <tanveermustafa94@gmail.com>
License: MIT
Project-URL: Homepage, https://github.com/android4561/xml-sanitizer
Keywords: xml,escaping,regex,parsing
Classifier: Programming Language :: Python :: 3
Classifier: License :: OSI Approved :: MIT License
Classifier: Operating System :: OS Independent
Requires-Python: >=3.8
License-File: LICENSE
Dynamic: license-file
